[
  {
    "guid": "3164f039-ae75-42af-9672-a7d408de2588",
    "title": "Education",
    "description": null
  },
  {
    "guid": "9fafced6-1f3d-4666-9a7a-61ffc423710c",
    "title": "Health Care",
    "description": null
  },
  {
    "guid": "dcdc2168-95c5-4c46-a796-f7297fda32cb",
    "title": "Older Person/ Senior Citizens",
    "description": null
  },
  {
    "guid": "3945fa26-2374-42bd-81fc-5b97794e4d0e",
    "title": "Youth",
    "description": null
  },
  {
    "guid": "b59753ef-a679-4dc3-aa0d-d8c07837ae88",
    "title": "Orphanage and Vulnerable Children (OVC)",
    "description": null
  },
  {
    "guid": "5d3dbbea-4a6b-44d4-8f57-7ae9e0d50228",
    "title": "Gender",
    "description": null
  },
  {
    "guid": "df7d7854-28a8-4239-b8fb-1517fbb8da9d",
    "title": "Human Rights",
    "description": null
  },
  {
    "guid": "cf41844e-335d-4cc0-b048-26dd2a800421",
    "title": "Environment",
    "description": null
  },
  {
    "guid": "3dc6ef26-bc9a-4478-8f85-7a8cceba273b",
    "title": "Trade",
    "description": null
  },
  {
    "guid": "a08583ba-2af8-4d25-b693-602b39d80e69",
    "title": "Poverty Alleviation",
    "description": null
  },
  {
    "guid": "4f508729-e0dd-4300-8191-7764568bd71f",
    "title": "Community Safety",
    "description": null
  },
  {
    "guid": "4f3c117d-7080-4baf-9812-54f8fe5ee91f",
    "title": "Communal Property Association (CPA)",
    "description": "Communal Property Association (CPA)"
  },
  {
    "guid": "8eaf5fac-be9f-45c0-b47f-1162fec305f7",
    "title": "Agriculture",
    "description": "Animal Husbandry"
  }
]